translator/__init__.py
translator/admin.py
translator/context_processors.py
translator/models.py
translator/translation.py
translator/util.py
translator/__pycache__/__init__.cpython-310.pyc
translator/__pycache__/admin.cpython-310.pyc
translator/__pycache__/context_processors.cpython-310.pyc
translator/__pycache__/models.cpython-310.pyc
translator/__pycache__/translation.cpython-310.pyc
translator/__pycache__/util.cpython-310.pyc
translator/templatetags/__init__.py
translator/templatetags/translator_tags.py
translator/templatetags/__pycache__/__init__.cpython-310.pyc
translator/templatetags/__pycache__/translator_tags.cpython-310.pyc
django_translator-1.1.0.dist-info/LICENSE
django_translator-1.1.0.dist-info/METADATA
django_translator-1.1.0.dist-info/WHEEL
django_translator-1.1.0.dist-info/top_level.txt
django_translator-1.1.0.dist-info/RECORD
