Metadata-Version: 2.1
Name: django-translator
Version: 1.1.0
Summary: Translator is an app for collecting translations for specified keys in django admin.
Home-page: https://www.dreipol.ch/
Author: dreipol GmbH
Author-email: dev@dreipol.ch
License: MIT License
Classifier: Environment :: Web Environment
Classifier: Framework :: Django
Classifier: Intended Audience :: Developers
Classifier: License :: OSI Approved :: MIT License
Classifier: Operating System :: OS Independent
Classifier: Programming Language :: Python
Classifier: Programming Language :: Python :: 3
Classifier: Topic :: Internet :: WWW/HTTP
Classifier: Topic :: Internet :: WWW/HTTP :: Dynamic Content
License-File: LICENSE
Requires-Dist: Django (>=3.2)
Requires-Dist: django-modeltranslation (>=0.18.4)
Requires-Dist: django-taggit (>=2.0.0)
